vcferr/__init__.py
vcferr/__main__.py
vcferr/err.py
vcferr-1.0.2.dist-info/LICENSE
vcferr-1.0.2.dist-info/METADATA
vcferr-1.0.2.dist-info/WHEEL
vcferr-1.0.2.dist-info/entry_points.txt
vcferr-1.0.2.dist-info/top_level.txt
vcferr-1.0.2.dist-info/RECORD
