Metadata-Version: 2.1
Name: vcferr
Version: 1.0.2
Summary: Probabilistic VCF genotype error simulation
Home-page: https://github.com/signaturescience/vcferr
License: MIT
Project-URL: Bug Reports, https://github.com/signaturescience/vcferr/issues
Platform: UNKNOWN
License-File: LICENSE
Requires-Dist: pysam
Requires-Dist: click
